competex/__init__.py
competex/main.py
competex-1.4.dist-info/LICENSE
competex-1.4.dist-info/METADATA
competex-1.4.dist-info/WHEEL
competex-1.4.dist-info/top_level.txt
competex-1.4.dist-info/RECORD
