Metadata-Version: 2.1
Name: competex
Version: 1.4
Summary: A Python library for analyzing competitors using data from social media platforms
Author-email: Sike Brothers <sikebros@gmail.com>
Classifier: Programming Language :: Python :: 3
Classifier: License :: OSI Approved :: MIT License
Classifier: Operating System :: OS Independent
Requires-Python: >=3
License-File: LICENSE
